base256/__init__.py
base256/__main__.py
base256-1.0.1.dist-info/LICENSE
base256-1.0.1.dist-info/METADATA
base256-1.0.1.dist-info/WHEEL
base256-1.0.1.dist-info/entry_points.txt
base256-1.0.1.dist-info/top_level.txt
base256-1.0.1.dist-info/RECORD
