Metadata-Version: 2.1
Name: base256
Version: 1.0.1
Summary: When base64 just isn't enough
Home-page: https://github.com/donno2048/base256
Author: Elisha Hollander
Author-email: just4now666666@gmail.com
License: MIT
Project-URL: Documentation, https://github.com/donno2048/base256#readme
Project-URL: Bug Reports, https://github.com/donno2048/base256/issues
Project-URL: Source Code, https://github.com/donno2048/base256
Platform: UNKNOWN
Requires-Python: >=3.0
License-File: LICENSE
